aesthetic_text/__init__.py
aesthetic_text/aesthetic_text.py
aesthetic_text-0.2.0.dist-info/METADATA
aesthetic_text-0.2.0.dist-info/WHEEL
aesthetic_text-0.2.0.dist-info/top_level.txt
aesthetic_text-0.2.0.dist-info/RECORD
