Metadata-Version: 2.1
Name: aesthetic_text
Version: 0.2.0
Summary: to stylized terminal text
Home-page: https://github.com/kyleex/aesthetic_text
Author: Kyleex
Author-email: antwill34@icloud.com
License: UNKNOWN
Platform: UNKNOWN
Classifier: Development Status :: 3 - Alpha
Classifier: License :: OSI Approved :: MIT License
Classifier: Programming Language :: Python :: 3
Classifier: Programming Language :: Python :: 3.8
